.gitignore
LICENSE
README.md
requirements.txt
setup.py
notebooks/README.md
notebooks/old_notebooks/EstimateDuration.ipynb
notebooks/old_notebooks/README.md
notebooks/old_notebooks/arxiv_scrape.ipynb
notebooks/old_notebooks/autoencoder.ipynb
notebooks/old_notebooks/cat_boost.ipynb
notebooks/old_notebooks/catboost_gpu.ipynb
notebooks/old_notebooks/check_gpu.ipynb
notebooks/old_notebooks/fcn_segmentation_model.ipynb
notebooks/old_notebooks/fn.ipynb
notebooks/old_notebooks/fuzzy_match_words_texts.ipynb
notebooks/old_notebooks/kaggle_datasets.ipynb
notebooks/old_notebooks/kera_multi_gpu.ipynb
notebooks/old_notebooks/keras_checkpoins.ipynb
notebooks/old_notebooks/keras_embedding.ipynb
notebooks/old_notebooks/keras_generator.ipynb
notebooks/old_notebooks/keras_save_load_model.ipynb
notebooks/old_notebooks/keras_time_distribution.ipynb
notebooks/old_notebooks/keras_tokenizer_fix.ipynb
notebooks/old_notebooks/label_encoding.ipynb
notebooks/old_notebooks/parallel_processing.ipynb
notebooks/old_notebooks/pretrain_transformer.ipynb
notebooks/old_notebooks/pytorch_nn.ipynb
notebooks/old_notebooks/seq2seq_translator.ipynb
notebooks/old_notebooks/test_mxnet.ipynb
notebooks/old_notebooks/text_sum_no_generator.ipynb
notebooks/old_notebooks/tpot_auto_ml.ipynb
notebooks/old_notebooks/universal_fuzzy_word_matching.ipynb
notebooks/old_notebooks/universal_sentence_embedding.ipynb
notebooks/old_notebooks/use_lime.ipynb
notebooks/old_notebooks/vanila_nn.ipynb
notebooks/old_notebooks/wget_google_drive.ipynb
notebooks/old_notebooks/word_embeddings_visualize.ipynb
notebooks/old_notebooks/word_sentence_similarity_transformers.ipynb
notebooks/old_notebooks/attention_mechanisms/.gitkeep
notebooks/old_notebooks/attention_mechanisms/tf2_0_attention_mechanisms.ipynb
notebooks/old_notebooks/learning_pytorch/README.md
notebooks/old_notebooks/learning_pytorch/pytorch_gpu.py
notebooks/old_notebooks/learning_pytorch/pytorch_nn.ipynb
src/ml_things.egg-info/PKG-INFO
src/ml_things.egg-info/SOURCES.txt
src/ml_things.egg-info/dependency_links.txt
src/ml_things.egg-info/requires.txt
src/ml_things.egg-info/top_level.txt
