Metadata-Version: 2.1
Name: ml-things
Version: 0.0.1
Summary: Useful functions when working with Machine Learning in Python
Home-page: https://github.com/gmihaila/ml_things
Author: George Mihaila
Author-email: georgemihaila@my.unt.edu
License: Apache
Keywords: NLP deep learning pytorch tensorflow numpy
Platform: UNKNOWN
Classifier: Development Status :: 5 - Production/Stable
Classifier: Intended Audience :: Developers
Classifier: Intended Audience :: Education
Classifier: Intended Audience :: Science/Research
Classifier: License :: OSI Approved :: Apache Software License
Classifier: Operating System :: OS Independent
Classifier: Programming Language :: Python :: 3
Classifier: Programming Language :: Python :: 3.6
Classifier: Programming Language :: Python :: 3.7
Classifier: Topic :: Scientific/Engineering :: Artificial Intelligence
Requires-Python: >=3.6.0
